README.txt
setup.py
um7/__init__.py
um7/tests.py
um7/um7.py
um7.egg-info/PKG-INFO
um7.egg-info/SOURCES.txt
um7.egg-info/dependency_links.txt
um7.egg-info/not-zip-safe
um7.egg-info/requires.txt
um7.egg-info/top_level.txt